prodigal_automation/auth.py
prodigal_automation/client.py
prodigal_automation/oauth.py
prodigal_automation/tools.py
prodigal_automation-0.1.1.dist-info/METADATA
prodigal_automation-0.1.1.dist-info/WHEEL
prodigal_automation-0.1.1.dist-info/RECORD
