Metadata-Version: 2.1
Name: prodigal-automation
Version: 0.1.1
Summary: Agentic tools & OAuth/RBAC support for Prodigal Automation
License: MIT
Author: Your Name
Author-email: you@company.com
Requires-Python: >=3.8,<4.0
Classifier: License :: OSI Approved :: MIT License
Classifier: Programming Language :: Python :: 3
Classifier: Programming Language :: Python :: 3.8
Classifier: Programming Language :: Python :: 3.9
Classifier: Programming Language :: Python :: 3.10
Classifier: Programming Language :: Python :: 3.11
Classifier: Programming Language :: Python :: 3.12
Requires-Dist: pydantic (>=2.1.1,<3.0.0)
Requires-Dist: requests (>=2.31.0,<3.0.0)
Requires-Dist: requests-oauthlib (>=1.3.1,<2.0.0)
